ProjectHelper/__init__.py
ProjectHelper/contacts_list.py
ProjectHelper/main.py
ProjectHelper/mynote.py
ProjectHelper/sort_files.py
personal_assistant-0.0.1.dist-info/LICENSE
personal_assistant-0.0.1.dist-info/METADATA
personal_assistant-0.0.1.dist-info/WHEEL
personal_assistant-0.0.1.dist-info/entry_points.txt
personal_assistant-0.0.1.dist-info/top_level.txt
personal_assistant-0.0.1.dist-info/RECORD
